MANIFEST.in
README.rst
setup.py
pleaseshare/__init__.py
pleaseshare/app.py
pleaseshare/default_settings.py
pleaseshare/forms.py
pleaseshare/static_routes.py
pleaseshare/tasks.py
pleaseshare/utils.py
pleaseshare.egg-info/PKG-INFO
pleaseshare.egg-info/SOURCES.txt
pleaseshare.egg-info/dependency_links.txt
pleaseshare.egg-info/requires.txt
pleaseshare.egg-info/top_level.txt
pleaseshare/static/normalize.css
pleaseshare/static/skeleton.css
pleaseshare/static/style.css
pleaseshare/static/fonts/OpenSans-Bold-webfont.eot
pleaseshare/static/fonts/OpenSans-Bold-webfont.svg
pleaseshare/static/fonts/OpenSans-Bold-webfont.ttf
pleaseshare/static/fonts/OpenSans-Bold-webfont.woff
pleaseshare/static/fonts/OpenSans-Light-webfont.eot
pleaseshare/static/fonts/OpenSans-Light-webfont.svg
pleaseshare/static/fonts/OpenSans-Light-webfont.ttf
pleaseshare/static/fonts/OpenSans-Light-webfont.woff
pleaseshare/static/fonts/OpenSans-Regular-webfont.eot
pleaseshare/static/fonts/OpenSans-Regular-webfont.svg
pleaseshare/static/fonts/OpenSans-Regular-webfont.ttf
pleaseshare/static/fonts/OpenSans-Regular-webfont.woff
pleaseshare/templates/about.html
pleaseshare/templates/base.html
pleaseshare/templates/contact.html
pleaseshare/templates/help.html
pleaseshare/templates/home.html
pleaseshare/templates/my_uploads.html
pleaseshare/templates/tos.html
pleaseshare/templates/view.html
pleaseshare/torrent/__init__.py
pleaseshare/torrent/bencode.py
pleaseshare/torrent/common.py
pleaseshare/torrent/maketorrent.py
pleaseshare/translations/fr/LC_MESSAGES/messages.mo
pleaseshare/translations/fr/LC_MESSAGES/messages.po