Metadata-Version: 1.1
Name: pleaseshare
Version: 0.5
Summary: A file-sharing web application
Home-page: http://pleaseshare.mathieui.net
Author: Mathieu Pasquet
Author-email: pleaseshare@mathieui.net
License: UNKNOWN
Download-URL: https://github.com/mathieui/pleaseshare/releases
Keywords: flask filesharing pleaseshare web
Platform: UNKNOWN
Classifier: Development Status :: 5 - Production/Stable
Classifier: Environment :: Web Environment
Classifier: Framework :: Flask
Classifier: Intended Audience :: Developers
Classifier: License :: OSI Approved :: GNU Affero General Public License v3
Classifier: Natural Language :: English
Classifier: Natural Language :: French
Classifier: Operating System :: POSIX :: Linux
Classifier: Programming Language :: JavaScript
Classifier: Programming Language :: Python :: 3.4
Classifier: Programming Language :: Python :: 3 :: Only
Classifier: Topic :: Text Processing :: Markup :: HTML
Classifier: Topic :: Communications :: File Sharing
Classifier: Topic :: Software Development :: Libraries :: Python Modules
